eArsivPortal/__init__.py
eArsivPortal/Core/Hatalar.py
eArsivPortal/Core/__init__.py
eArsivPortal/Libs/FaturaVer.py
eArsivPortal/Libs/KurGetir.py
eArsivPortal/Libs/Oturum.py
eArsivPortal/Libs/__init__.py
eArsivPortal/Models/Komutlar.py
eArsivPortal/Models/__init__.py
eArsivPortal-1.1.0.dist-info/LICENSE
eArsivPortal-1.1.0.dist-info/METADATA
eArsivPortal-1.1.0.dist-info/WHEEL
eArsivPortal-1.1.0.dist-info/top_level.txt
eArsivPortal-1.1.0.dist-info/RECORD
