Metadata-Version: 2.1
Name: eArsivPortal
Version: 1.1.0
Summary: GİB e-Arşiv Portal e-Fatura Oluşturucu
Home-page: https://github.com/keyiflerolsun/eArsivPortal
Author: keyiflerolsun
Author-email: keyiflerolsun@gmail.com
License: GPLv3+
Keywords: eArsivPortal,KekikAkademi,keyiflerolsun
Classifier: Development Status :: 5 - Production/Stable
Classifier: License :: OSI Approved :: GNU General Public License v3 or later (GPLv3+)
Classifier: Programming Language :: Python :: 3
Requires-Python: >=3.10
License-File: LICENSE
Requires-Dist: setuptools
Requires-Dist: wheel
Requires-Dist: urllib3
Requires-Dist: requests
Requires-Dist: pydantic
Requires-Dist: parsel
Requires-Dist: cssselect
Requires-Dist: xmltodict
